adbtv/__init__.py
adbtv/adbcte.py
adbtv/base.py
adbtv-0.0.2.dist-info/LICENSE
adbtv-0.0.2.dist-info/METADATA
adbtv-0.0.2.dist-info/WHEEL
adbtv-0.0.2.dist-info/top_level.txt
adbtv-0.0.2.dist-info/RECORD
