Metadata-Version: 2.1
Name: adbtv
Version: 0.0.2
Summary: A simple ADB package
Home-page: UNKNOWN
Author: Luis Gustavo Lang Gaiato
Author-email: lang.gaiato@ufrgs.br
License: MIT
Keywords: adb,androidtv
Platform: UNKNOWN
Classifier: Development Status :: 3 - Alpha
Classifier: Intended Audience :: Developers
Classifier: License :: OSI Approved :: MIT License
Classifier: Programming Language :: Python :: 3
Requires-Dist: typing
